tdrpa/tdcreator.cp38-win_amd64.pyd
tdrpa/tdcreator/res/icon/new_file.png
tdrpa/tdcreator/res/icon/open_file.png
tdrpa/tdcreator/res/icon/open_folder.png
tdrpa/tdcreator/res/icon/run.png
tdrpa/tdcreator/res/icon/save_all.png
tdrpa/tdcreator/res/icon/save_file.png
tdrpa.tdcreator-0.0.6.dist-info/METADATA
tdrpa.tdcreator-0.0.6.dist-info/WHEEL
tdrpa.tdcreator-0.0.6.dist-info/entry_points.txt
tdrpa.tdcreator-0.0.6.dist-info/top_level.txt
tdrpa.tdcreator-0.0.6.dist-info/RECORD
