Metadata-Version: 2.1
Name: tdrpa.tdcreator
Version: 0.0.6
Summary: RPA SDK for software developers. Supports Python3.7+, Windows x64
Home-page: https://tdrpa.thingswell.cn
Author: tdrpa
Author-email: armstrong.wang@gmail.com
License: Apache 2.0
Keywords: RPA,tdRPA,uiautomation,uia
Platform: Windows Only
Classifier: Programming Language :: Python :: 3
Classifier: Operating System :: Microsoft :: Windows
Requires-Dist: Requests
Requires-Dist: tzlocal
Requires-Dist: QScintilla
